claptcha/__init__.py
claptcha/claptcha.py
claptcha-0.3.3.dist-info/DESCRIPTION.rst
claptcha-0.3.3.dist-info/METADATA
claptcha-0.3.3.dist-info/RECORD
claptcha-0.3.3.dist-info/WHEEL
claptcha-0.3.3.dist-info/metadata.json
claptcha-0.3.3.dist-info/top_level.txt
