Metadata-Version: 2.0
Name: claptcha
Version: 0.3.3
Summary: A simple CAPTCHA image generator
Home-page: https://github.com/kuszaj/claptcha/
Author: Piotr Kuszaj
Author-email: peterkuszaj@gmail.com
License: MIT
Platform: UNKNOWN
Classifier: Development Status :: 3 - Alpha
Classifier: Intended Audience :: Developers
Classifier: License :: OSI Approved :: MIT License
Classifier: Operating System :: MacOS :: MacOS X
Classifier: Operating System :: Microsoft :: Windows
Classifier: Operating System :: POSIX :: Linux
Classifier: Programming Language :: Python :: 3
Classifier: Programming Language :: Python :: 3.5
Classifier: Topic :: Multimedia :: Graphics
Classifier: Topic :: Software Development :: Libraries :: Python Modules
Requires-Dist: Pillow
